pycomando/__init__.py
pycomando/comando.py
pycomando/pycomando.py
pycomando-0.2.0.data/data/share/pycomando/LICENSE
pycomando-0.2.0.data/data/share/pycomando/README.md
pycomando-0.2.0.data/data/share/pycomando/examples/ejemplo1.py
pycomando-0.2.0.dist-info/LICENSE
pycomando-0.2.0.dist-info/METADATA
pycomando-0.2.0.dist-info/WHEEL
pycomando-0.2.0.dist-info/entry_points.txt
pycomando-0.2.0.dist-info/top_level.txt
pycomando-0.2.0.dist-info/RECORD
