Metadata-Version: 2.1
Name: pycomando
Version: 0.2.0
Summary: Wrapper command
Home-page: https://gitlab.com/doberti/pycomando
Download-URL: http://pypi.python.org/pypi/pycomando/
Author: Daniel Oberti
Author-email: obertidaniel@gmail.com
License: MIT
Platform: any
Classifier: Programming Language :: Python :: 3
Classifier: License :: OSI Approved :: MIT License
Classifier: Operating System :: OS Independent
Requires-Python: >=3.7
License-File: LICENSE
Requires-Dist: argcomplete
Requires-Dist: rich
Requires-Dist: tabulate
Requires-Dist: redis
Requires-Dist: pandas
Requires-Dist: eland
Requires-Dist: elasticsearch
Requires-Dist: PyYAML
